splatoon2_tools/__init__.py
splatoon2_tools/config.py
splatoon2_tools/core.py
splatoon2_tools/tests.py
splatoon2_tools/utils.py
nanobot_plugin_splatoon2tools-1.3.1.dist-info/LICENSE
nanobot_plugin_splatoon2tools-1.3.1.dist-info/METADATA
nanobot_plugin_splatoon2tools-1.3.1.dist-info/WHEEL
nanobot_plugin_splatoon2tools-1.3.1.dist-info/top_level.txt
nanobot_plugin_splatoon2tools-1.3.1.dist-info/RECORD
