Metadata-Version: 2.1
Name: nanobot-plugin-splatoon2tools
Version: 1.3.1
Summary: splatoon2 tools bot
Home-page: https://github.com/DrinkOolongTea/splatong2-bot
Author: DrinkOolongTea
Author-email: sh.elsyion@qq.com
License: GNU General Public License v3.0
Platform: UNKNOWN
Classifier: Programming Language :: Python :: 3
Classifier: License :: OSI Approved :: GNU General Public License v3 (GPLv3)
Classifier: Operating System :: OS Independent
License-File: LICENSE
Requires-Dist: lxml
Requires-Dist: Pillow
Requires-Dist: nonebot2
Requires-Dist: nonebot-adapter-onebot
